{
  "collectionName": "components_nombre_medicamento_farmacias",
  "info": {
    "displayName": "Farmacia",
    "icon": "earth"
  },
  "options": {},
  "attributes": {
    "Imagen": {
      "type": "media",
      "multiple": true,
      "allowedTypes": [
        "images",
        "files",
        "videos",
        "audios"
      ]
    },
    "Nombremedicamento": {
      "type": "string"
    },
    "Contenido": {
      "type": "string"
    },
    "CompuestoActivo": {
      "type": "string"
    },
    "Presentacion": {
      "type": "enumeration",
      "enum": [
        "Tableta",
        "Spray",
        "Crema",
        "Gel",
        "Solucion",
        "Suspencion"
      ]
    },
    "Categoria": {
      "type": "enumeration",
      "enum": [
        "Analgesicos",
        "Antinflamatorios",
        "Vitaminas",
        "Antibiotico"
      ]
    }
  },
  "config": {}
}
